CHANGELOG.md
gridplayer/__init__.py
gridplayer/__main__.py
gridplayer/dialogs/__init__.py
gridplayer/dialogs/about.py
gridplayer/dialogs/about_dialog_ui.py
gridplayer/dialogs/add_urls.py
gridplayer/dialogs/exception.py
gridplayer/dialogs/exception_dialog_ui.py
gridplayer/dialogs/input_dialog.py
gridplayer/dialogs/messagebox.py
gridplayer/dialogs/rename_dialog.py
gridplayer/dialogs/settings.py
gridplayer/dialogs/settings_dialog_ui.py
gridplayer/exceptions.py
gridplayer/main/__init__.py
gridplayer/main/init_app.py
gridplayer/main/init_app_env.py
gridplayer/main/init_icons.py
gridplayer/main/init_log.py
gridplayer/main/init_resources.py
gridplayer/main/init_translator.py
gridplayer/main/run.py
gridplayer/models/__init__.py
gridplayer/models/grid_state.py
gridplayer/models/playlist.py
gridplayer/models/recent_list.py
gridplayer/models/resolver_patterns.py
gridplayer/models/stream.py
gridplayer/models/video.py
gridplayer/models/video_uri.py
gridplayer/multiprocess/__init__.py
gridplayer/multiprocess/command_loop.py
gridplayer/multiprocess/instance_process.py
gridplayer/multiprocess/process_manager.py
gridplayer/multiprocess/safe_shared_memory.py
gridplayer/params/__init__.py
gridplayer/params/actions.py
gridplayer/params/env.py
gridplayer/params/extensions.py
gridplayer/params/languages.py
gridplayer/params/menu.py
gridplayer/params/static.py
gridplayer/player/__init__.py
gridplayer/player/manager.py
gridplayer/player/managers/__init__.py
gridplayer/player/managers/actions.py
gridplayer/player/managers/active_block.py
gridplayer/player/managers/add_videos.py
gridplayer/player/managers/base.py
gridplayer/player/managers/dialogs.py
gridplayer/player/managers/drag_n_drop.py
gridplayer/player/managers/grid.py
gridplayer/player/managers/instance_listener.py
gridplayer/player/managers/log.py
gridplayer/player/managers/macos_fileopen.py
gridplayer/player/managers/menu.py
gridplayer/player/managers/mouse_hide.py
gridplayer/player/managers/playlist.py
gridplayer-0.5.2.dist-info/LICENSE
gridplayer-0.5.2.dist-info/METADATA
gridplayer-0.5.2.dist-info/WHEEL
gridplayer-0.5.2.dist-info/entry_points.txt
gridplayer-0.5.2.dist-info/RECORD
