Metadata-Version: 2.1
Name: gridplayer
Version: 0.5.2
Summary: Play videos side-by-side
Home-page: https://github.com/vzhd1701/gridplayer
License: GPL-3.0-or-later
Keywords: video,player,vlc,pyqt,Qt5,multimedia
Author: vzhd1701
Author-email: vzhd1701@gmail.com
Requires-Python: >=3.8.1,<4.0.0
Classifier: Development Status :: 4 - Beta
Classifier: Environment :: X11 Applications :: Qt
Classifier: Intended Audience :: End Users/Desktop
Classifier: License :: OSI Approved :: GNU General Public License v3 or later (GPLv3+)
Classifier: Natural Language :: English
Classifier: Operating System :: MacOS
Classifier: Operating System :: Microsoft
Classifier: Operating System :: Unix
Classifier: Programming Language :: Python :: 3
Classifier: Programming Language :: Python :: 3.9
Classifier: Programming Language :: Python :: 3.10
Classifier: Programming Language :: Python :: 3.11
Classifier: Topic :: Multimedia :: Video :: Display
Requires-Dist: PyQt5 (==5.15.7)
Requires-Dist: pydantic (>=1.8.2,<2.0.0)
Requires-Dist: pyobjc-core ; sys_platform == "darwin"
Requires-Dist: pyobjc-framework-Cocoa ; sys_platform == "darwin"
Requires-Dist: python-vlc (==3.0.11115)
Requires-Dist: streamlink (==6.1.0)
Requires-Dist: yt-dlp (==2023.7.6)
Project-URL: Changelog, https://github.com/vzhd1701/gridplayer/blob/master/CHANGELOG.md
Project-URL: Repository, https://github.com/vzhd1701/gridplayer
